simple_template_log_parser/__init__.py
simple_template_log_parser/column_functions.py
simple_template_log_parser/log_functions.py
simple_template_log_parser/log_type_classes.py
simple_template_log_parser/omada.py
simple_template_log_parser/omada_templates.py
simple_template_log_parser/sample.py
simple_template_log_parser/synology.py
simple_template_log_parser/synology_templates.py
simple_template_log_parser-0.1.dist-info/LICENSE
simple_template_log_parser-0.1.dist-info/METADATA
simple_template_log_parser-0.1.dist-info/WHEEL
simple_template_log_parser-0.1.dist-info/top_level.txt
simple_template_log_parser-0.1.dist-info/RECORD
