Metadata-Version: 2.1
Name: simple_template_log_parser
Version: 0.1
Summary: Parsing Log Files With User Defined Templates
Author-email: Caleb Yourison <caleb.yourison@gmail.com>
Keywords: log,parse,template
Classifier: Development Status :: 3 - Alpha
Classifier: Programming Language :: Python
Requires-Python: >=3.8
License-File: LICENSE
Requires-Dist: pandas >=2.0.0
Requires-Dist: parse ==1.20.2
